cwf2neo/__init__.py
cwf2neo/config_default.yaml
cwf2neo/cwf2neo.py
cwf2neo/graph_objects.py
cwf2neo/neo4j.py
cwf2neo/utils.py
cwf2neo-0.77.0.dist-info/LICENSE.txt
cwf2neo-0.77.0.dist-info/METADATA
cwf2neo-0.77.0.dist-info/WHEEL
cwf2neo-0.77.0.dist-info/top_level.txt
cwf2neo-0.77.0.dist-info/RECORD
